MANIFEST.in
README.rst
setup.cfg
setup.py
tests/__init__.py
tests/base.py
tests/test_controller.py
tests/controllers/__init__.py
tests/controllers/root.py
tests/templates/__init__.py
tgapp_categories.egg-info/PKG-INFO
tgapp_categories.egg-info/SOURCES.txt
tgapp_categories.egg-info/dependency_links.txt
tgapp_categories.egg-info/entry_points.txt
tgapp_categories.egg-info/not-zip-safe
tgapp_categories.egg-info/requires.txt
tgapp_categories.egg-info/top_level.txt
tgappcategories/__init__.py
tgappcategories/bootstrap.py
tgappcategories/helpers.py
tgappcategories/partials.py
tgappcategories/controllers/__init__.py
tgappcategories/controllers/root.py
tgappcategories/lib/__init__.py
tgappcategories/lib/forms.py
tgappcategories/migration/env.py
tgappcategories/migration/script.py.mako
tgappcategories/migration/versions/7e81e2d2f737_enable_multi_level_categories.py
tgappcategories/migration/versions/7e81e2d2f737_enable_multi_level_categories.py~
tgappcategories/migration/versions/empty.txt
tgappcategories/model/__init__.py
tgappcategories/model/ming/__init__.py
tgappcategories/model/ming/models.py
tgappcategories/model/sqla/__init__.py
tgappcategories/model/sqla/models.py
tgappcategories/public/__init__.py
tgappcategories/public/css/style.css
tgappcategories/public/images/star.png
tgappcategories/templates/__init__.py
tgappcategories/templates/edit_category.xhtml
tgappcategories/templates/index.xhtml
tgappcategories/templates/new_category.xhtml